SB14009UNO/__init__.py
SB14009UNO/biseccion.py
SB14009UNO/cramer.py
SB14009UNO/gauss.py
SB14009UNO/gauss_jordan.py
SB14009UNO/gauss_seidel.py
SB14009UNO/jacobi.py
SB14009UNO/lu_solve.py
sb14009uno-0.1.1.dist-info/licenses/LICENCE
sb14009uno-0.1.1.dist-info/METADATA
sb14009uno-0.1.1.dist-info/WHEEL
sb14009uno-0.1.1.dist-info/top_level.txt
sb14009uno-0.1.1.dist-info/RECORD
