Metadata-Version: 2.4
Name: SB14009UNO
Version: 0.1.1
Summary: Librería para resolver sistemas de ecuaciones
Author: Oscar Santos
Author-email: sb14009@ues.edu.sv
License: MIT
License-File: LICENCE
Requires-Dist: numpy
Dynamic: author
Dynamic: author-email
Dynamic: description
Dynamic: description-content-type
Dynamic: license
Dynamic: license-file
Dynamic: requires-dist
Dynamic: summary
